center_of_mass/__init__.py
center_of_mass/estimator.py
center_of_mass/kinematic.py
center_of_mass-1.0.1.dist-info/LICENSE
center_of_mass-1.0.1.dist-info/WHEEL
center_of_mass-1.0.1.dist-info/METADATA
center_of_mass-1.0.1.dist-info/RECORD
