Metadata-Version: 2.1
Name: center_of_mass
Version: 1.0.1
Summary: Calculation of the body center of mass from the kinematics (kinematic) and through optimal combination of kinematic and kinetic information (estimator)
Author-email: Charlotte Le Mouel <charlotte.lemouel@normale.fr>
Classifier: License :: OSI Approved :: MIT License
Requires-Dist: numpy>=1.24
Requires-Dist: sphinx ; extra == "documentation"
Requires-Dist: nbsphinx ; extra == "documentation"
Requires-Dist: numpydoc ; extra == "documentation"
Requires-Dist: sphinx-rtd-theme ; extra == "documentation"
Requires-Dist: myst-parser ; extra == "documentation"
Requires-Dist: ipython ; extra == "documentation"
Requires-Dist: matplotlib ; extra == "tutorials"
Requires-Dist: jupyter ; extra == "tutorials"
Project-URL: Documentation, https://center-of-mass.readthedocs.io/
Project-URL: Homepage, https://github.com/charlotte-lemouel/center_of_mass
Provides-Extra: documentation
Provides-Extra: tutorials
